auto_genetic/__init__.py
auto_genetic/algorithm.py
auto_genetic/darwinism.py
auto_genetic/evaluation/__init__.py
auto_genetic/evaluation/evaluator.py
auto_genetic/evaluation/feature_selector.py
auto_genetic/evaluation/fitness_functions.py
auto_genetic/evaluation/fitnessfuncsetter.py
auto_genetic/evaluation/metrics.py
auto_genetic/population_initializer/__init__.py
auto_genetic/population_initializer/chromosomes.py
auto_genetic/population_initializer/feature_setter.py
auto_genetic/population_initializer/hyperparams_setter.py
auto_genetic/population_initializer/population.py
auto_genetic/program_base.py
auto_genetic/reproduction/__init__.py
auto_genetic/reproduction/crossover.py
auto_genetic/reproduction/mutation.py
auto_genetic/reproduction/reproduction.py
auto_genetic/reproduction/selection.py
auto_genetic/reproduction/translation.py
auto_genetic-0.1.0.dist-info/WHEEL
auto_genetic-0.1.0.dist-info/METADATA
auto_genetic-0.1.0.dist-info/RECORD
